{
	"configurations" : 
	[
		{
			"directories" : 
			[
				{
					"build" : ".",
					"jsonFile" : "directory-.-Debug-d0094a50bb2071803777.json",
					"minimumCMakeVersion" : 
					{
						"string" : "3.26"
					},
					"projectIndex" : 0,
					"source" : "."
				}
			],
			"name" : "Debug",
			"projects" : 
			[
				{
					"directoryIndexes" : 
					[
						0
					],
					"name" : "Project"
				}
			],
			"targets" : []
		}
	],
	"kind" : "codemodel",
	"paths" : 
	{
		"build" : "C:/Users/\u0420\u0430\u0443\u0444/IvanOOP6/OOP_Labs-main/lab6/include/out/build/x64-Debug",
		"source" : "C:/Users/\u0420\u0430\u0443\u0444/IvanOOP6/OOP_Labs-main/lab6/include"
	},
	"version" : 
	{
		"major" : 2,
		"minor" : 6
	}
}
